{
  "data": {
    "article": {},
    "attachments": {},
    "author_id": "2063187473405227008",
    "conversation_id": "2076888565263581428",
    "created_at": "2026-07-14T16:56:11.000Z",
    "edit_controls": {
      "editable_until": "2026-07-14T17:56:11.000Z",
      "edits_remaining": 5,
      "is_edit_eligible": false
    },
    "edit_history_tweet_ids": [
      "2077074693044023297"
    ],
    "entities": {
      "mentions": [
        {
          "end": 14,
          "id": "2071079328910299136",
          "start": 0,
          "username": "udonmaster123"
        }
      ]
    },
    "geo": {},
    "id": "2077074693044023297",
    "in_reply_to_user_id": "2071079328910299136",
    "lang": "en",
    "note_tweet": {
      "entities": {}
    },
    "possibly_sensitive": false,
    "public_metrics": {
      "bookmark_count": 0,
      "impression_count": 0,
      "like_count": 1,
      "quote_count": 0,
      "reply_count": 0,
      "retweet_count": 0
    },
    "referenced_tweets": [
      {
        "id": "2076888565263581428",
        "type": "replied_to"
      }
    ],
    "reply_settings": "everyone",
    "text": "@udonmaster123 You are as cute as Miku"
  },
  "includes": {
    "media": [
      {
        "height": 1440,
        "media_key": "3_2076888559475359744",
        "public_metrics": {},
        "type": "photo",
        "url": "https://pbs.twimg.com/media/HNKXJBmaAAAogzP.jpg",
        "width": 1080
      }
    ],
    "tweets": [
      {
        "article": {},
        "attachments": {},
        "author_id": "2063187473405227008",
        "conversation_id": "2076888565263581428",
        "created_at": "2026-07-14T16:56:11.000Z",
        "edit_controls": {
          "editable_until": "2026-07-14T17:56:11.000Z",
          "edits_remaining": 5,
          "is_edit_eligible": false
        },
        "edit_history_tweet_ids": [
          "2077074693044023297"
        ],
        "entities": {
          "mentions": [
            {
              "end": 14,
              "id": "2071079328910299136",
              "start": 0,
              "username": "udonmaster123"
            }
          ]
        },
        "geo": {},
        "id": "2077074693044023297",
        "in_reply_to_user_id": "2071079328910299136",
        "lang": "en",
        "note_tweet": {
          "entities": {}
        },
        "possibly_sensitive": false,
        "public_metrics": {
          "bookmark_count": 0,
          "impression_count": 0,
          "like_count": 1,
          "quote_count": 0,
          "reply_count": 0,
          "retweet_count": 0
        },
        "referenced_tweets": [
          {
            "id": "2076888565263581428",
            "type": "replied_to"
          }
        ],
        "reply_settings": "everyone",
        "text": "@udonmaster123 You are as cute as Miku"
      },
      {
        "article": {},
        "attachments": {
          "media_keys": [
            "3_2076888559475359744"
          ]
        },
        "author_id": "2071079328910299136",
        "conversation_id": "2076888565263581428",
        "created_at": "2026-07-14T04:36:35.000Z",
        "edit_controls": {
          "editable_until": "2026-07-14T05:36:35.000Z",
          "edits_remaining": 5,
          "is_edit_eligible": true
        },
        "edit_history_tweet_ids": [
          "2076888565263581428"
        ],
        "entities": {
          "urls": [
            {
              "display_url": "pic.x.com/4KyxX9ysxs",
              "end": 35,
              "expanded_url": "https://x.com/udonmaster123/status/2076888565263581428/photo/1",
              "media_key": "3_2076888559475359744",
              "start": 12,
              "url": "https://t.co/4KyxX9ysxs"
            }
          ]
        },
        "geo": {},
        "id": "2076888565263581428",
        "lang": "in",
        "note_tweet": {
          "entities": {}
        },
        "possibly_sensitive": false,
        "public_metrics": {
          "bookmark_count": 2,
          "impression_count": 831,
          "like_count": 95,
          "quote_count": 0,
          "reply_count": 3,
          "retweet_count": 4
        },
        "reply_settings": "everyone",
        "text": "Oi miku san https://t.co/4KyxX9ysxs"
      }
    ],
    "users": [
      {
        "created_at": "2026-06-06T09:14:15.000Z",
        "description": "17//叫我小雨就好了//互关和扩列私我//同好可直接互关//偶尔更新//bilibili 宅小雨rain",
        "id": "2063187473405227008",
        "name": "雨雨子",
        "pinned_tweet_id": "2067589871783588060",
        "profile_image_url": "https://pbs.twimg.com/profile_images/2067229260100853760/id2JxlXU_normal.jpg",
        "protected": false,
        "public_metrics": {
          "followers_count": 645,
          "following_count": 105,
          "like_count": 1138,
          "listed_count": 1,
          "media_count": 24,
          "tweet_count": 173
        },
        "url": "",
        "username": "yvame_rain",
        "verified": true
      },
      {
        "created_at": "2026-06-28T03:53:46.000Z",
        "description": "Hello I am udonmaster ദ്ദി ᗜˬᗜ✧ I love cat girls and cute girls (*´꒳`*) just rant and cosplay ニャー 🐾",
        "id": "2071079328910299136",
        "location": "猫ランド",
        "name": "haru",
        "pinned_tweet_id": "2075283315364712655",
        "profile_image_url": "https://pbs.twimg.com/profile_images/2075745094561677312/fcStvEQd_normal.jpg",
        "protected": false,
        "public_metrics": {
          "followers_count": 900,
          "following_count": 46,
          "like_count": 1776,
          "listed_count": 1,
          "media_count": 49,
          "tweet_count": 329
        },
        "url": "",
        "username": "udonmaster123",
        "verified": false
      }
    ]
  }
}